{
  "Code": "000",
  "Message": "操作成功！",
  "Result": "{\"tmallShopName\":\"树懒熊\",\"total\":27,\"shareSubTitle\":null,\"title\":\"开门红\",\"distance\":\"575620.6860324187\",\"tmallShopLogo\":\"http://yycmedia.image.alimmdn.com/ldy/2017/01faea9d-43e3-4450-b5f3-995c8b040102.jpg\",\"shareIconUrl\":null,\"homeDataList\":[{\"modularId\":136391,\"modularType\":\"0\",\"modularStyle\":\"2\",\"modularHeight\":\"283\",\"modularWidth\":\"0\",\"modularScale\":null,\"modularTitle\":\"\",\"modularSubTitle\":\"\",\"isShowSpace\":\"0\",\"modularDataList\":[{\"advertisementId\":2550971,\"title\":null,\"memo\":null,\"bannerUrl\":\"http://yycmedia.image.alimmdn.com/ldy/2017/936a27c6-3e9f-4a3f-93f6-0575aaf40a06.jpg\",\"content\":null,\"advertisementType\":\"2\",\"linkId\":\"476362\",\"itemType\":\"1\",\"isCollect\":\"0\",\"price\":\"99.00\",\"memberPrice\":\"89.00\",\"svipLabel\":null,\"isPreSale\":\"0\",\"advertisementTitle\":null,\"discountType\":\"0\",\"isOpenItemProperty\":\"1\",\"height\":283,\"width\":375,\"advertisementWidth\":\"0\",\"linkValue\":null},{\"advertisementId\":2550972,\"title\":null,\"memo\":null,\"bannerUrl\":\"http://yycmedia.image.alimmdn.com/ldy/2017/a0c0a7ed-36f3-40d3-958b-6424a72edb3c.jpg\",\"content\":null,\"advertisementType\":\"2\",\"linkId\":\"949536\",\"itemType\":\"1\",\"isCollect\":\"0\",\"price\":\"36.00\",\"memberPrice\":\"32.00\",\"svipLabel\":null,\"isPreSale\":\"0\",\"advertisementTitle\":null,\"discountType\":\"0\",\"isOpenItemProperty\":\"1\",\"height\":283,\"width\":375,\"advertisementWidth\":\"0\",\"linkValue\":null}]},{\"modularId\":136403,\"modularType\":\"0\",\"modularStyle\":\"2\",\"modularHeight\":\"324\",\"modularWidth\":\"0\",\"modularScale\":null,\"modularTitle\":\"\",\"modularSubTitle\":\"\",\"isShowSpace\":\"0\",\"modularDataList\":[{\"advertisementId\":2550973,\"title\":null,\"memo\":null,\"bannerUrl\":\"http://yycmedia.image.alimmdn.com/ldy/2017/d7edb439-fd19-489c-96d6-4b35974b10f5.jpg\",\"content\":null,\"advertisementType\":\"2\",\"linkId\":\"1486691\",\"itemType\":\"1\",\"isCollect\":\"0\",\"price\":\"349.00\",\"memberPrice\":\"329.00\",\"svipLabel\":null,\"isPreSale\":\"0\",\"advertisementTitle\":null,\"discountType\":\"0\",\"isOpenItemProperty\":\"1\",\"height\":324,\"width\":375,\"advertisementWidth\":\"0\",\"linkValue\":null},{\"advertisementId\":2550974,\"title\":null,\"memo\":null,\"bannerUrl\":\"http://yycmedia.image.alimmdn.com/ldy/2017/549bacea-6278-4c9d-9acb-72d90e0bb629.jpg\",\"content\":null,\"advertisementType\":\"2\",\"linkId\":\"891700\",\"itemType\":\"1\",\"isCollect\":\"0\",\"price\":\"320.00\",\"memberPrice\":\"309.00\",\"svipLabel\":null,\"isPreSale\":\"0\",\"advertisementTitle\":null,\"discountType\":\"0\",\"isOpenItemProperty\":\"1\",\"height\":324,\"width\":375,\"advertisementWidth\":\"0\",\"linkValue\":null}]},{\"modularId\":136392,\"modularType\":\"0\",\"modularStyle\":\"0\",\"modularHeight\":\"166\",\"modularWidth\":\"0\",\"modularScale\":null,\"modularTitle\":\"\",\"modularSubTitle\":\"\",\"isShowSpace\":\"0\",\"modularDataList\":[{\"advertisementId\":2550975,\"title\":null,\"memo\":null,\"bannerUrl\":\"http://yycmedia.image.alimmdn.com/ldy/2017/a179d3c5-1582-46aa-b65b-340ac5b6611d.jpg\",\"content\":null,\"advertisementType\":\"0\",\"linkId\":\"0\",\"itemType\":null,\"isCollect\":\"0\",\"price\":null,\"memberPrice\":null,\"svipLabel\":null,\"isPreSale\":null,\"advertisementTitle\":null,\"discountType\":null,\"isOpenItemProperty\":null,\"height\":166,\"width\":750,\"advertisementWidth\":\"0\",\"linkValue\":null}]},{\"modularId\":136393,\"modularType\":\"0\",\"modularStyle\":\"2\",\"modularHeight\":\"360\",\"modularWidth\":\"0\",\"modularScale\":null,\"modularTitle\":\"\",\"modularSubTitle\":\"\",\"isShowSpace\":\"0\",\"modularDataList\":[{\"advertisementId\":2550976,\"title\":null,\"memo\":null,\"bannerUrl\":\"http://yycmedia.image.alimmdn.com/ldy/2017/9a1850a2-bb72-4f21-86e6-e8436f1edf00.jpg\",\"content\":null,\"advertisementType\":\"2\",\"linkId\":\"1485931\",\"itemType\":\"1\",\"isCollect\":\"0\",\"price\":\"79.00\",\"memberPrice\":\"79.00\",\"svipLabel\":null,\"isPreSale\":\"0\",\"advertisementTitle\":null,\"discountType\":\"0\",\"isOpenItemProperty\":\"1\",\"height\":360,\"width\":375,\"advertisementWidth\":\"0\",\"linkValue\":null},{\"advertisementId\":2550977,\"title\":null,\"memo\":null,\"bannerUrl\":\"http://yycmedia.image.alimmdn.com/ldy/2017/565806b0-5ee4-45bb-8bc9-d1dc4e49208d.jpg\",\"content\":null,\"advertisementType\":\"2\",\"linkId\":\"1487352\",\"itemType\":\"1\",\"isCollect\":\"0\",\"price\":\"349.00\",\"memberPrice\":\"349.00\",\"svipLabel\":null,\"isPreSale\":\"0\",\"advertisementTitle\":null,\"discountType\":\"0\",\"isOpenItemProperty\":\"1\",\"height\":360,\"width\":375,\"advertisementWidth\":\"0\",\"linkValue\":null}]},{\"modularId\":136394,\"modularType\":\"0\",\"modularStyle\":\"2\",\"modularHeight\":\"294\",\"modularWidth\":\"0\",\"modularScale\":null,\"modularTitle\":\"\",\"modularSubTitle\":\"\",\"isShowSpace\":\"0\",\"modularDataList\":[{\"advertisementId\":2550978,\"title\":null,\"memo\":null,\"bannerUrl\":\"http://yycmedia.image.alimmdn.com/ldy/2017/89ba25e5-7492-42f5-8210-2f3109523860.jpg\",\"content\":null,\"advertisementType\":\"2\",\"linkId\":\"1464163\",\"itemType\":\"1\",\"isCollect\":\"0\",\"price\":\"119.00\",\"memberPrice\":\"114.00\",\"svipLabel\":null,\"isPreSale\":\"0\",\"advertisementTitle\":null,\"discountType\":\"0\",\"isOpenItemProperty\":\"0\",\"height\":294,\"width\":375,\"advertisementWidth\":\"0\",\"linkValue\":null},{\"advertisementId\":2550979,\"title\":null,\"memo\":null,\"bannerUrl\":\"http://yycmedia.image.alimmdn.com/ldy/2017/d1c251f5-5186-46e8-a372-62cb561f7170.jpg\",\"content\":null,\"advertisementType\":\"2\",\"linkId\":\"1485902\",\"itemType\":\"1\",\"isCollect\":\"0\",\"price\":\"109.00\",\"memberPrice\":\"109.00\",\"svipLabel\":null,\"isPreSale\":\"0\",\"advertisementTitle\":null,\"discountType\":\"0\",\"isOpenItemProperty\":\"1\",\"height\":294,\"width\":375,\"advertisementWidth\":\"0\",\"linkValue\":null}]},{\"modularId\":136395,\"modularType\":\"0\",\"modularStyle\":\"2\",\"modularHeight\":\"267\",\"modularWidth\":\"0\",\"modularScale\":null,\"modularTitle\":\"\",\"modularSubTitle\":\"\",\"isShowSpace\":\"0\",\"modularDataList\":[{\"advertisementId\":2550980,\"title\":null,\"memo\":null,\"bannerUrl\":\"http://yycmedia.image.alimmdn.com/ldy/2017/5e2b4730-33b9-40f2-9e85-aede8e3ae22f.jpg\",\"content\":null,\"advertisementType\":\"2\",\"linkId\":\"1487354\",\"itemType\":\"1\",\"isCollect\":\"0\",\"price\":\"469.00\",\"memberPrice\":\"458.00\",\"svipLabel\":null,\"isPreSale\":\"0\",\"advertisementTitle\":null,\"discountType\":\"0\",\"isOpenItemProperty\":\"1\",\"height\":267,\"width\":375,\"advertisementWidth\":\"0\",\"linkValue\":null},{\"advertisementId\":2550981,\"title\":null,\"memo\":null,\"bannerUrl\":\"http://yycmedia.image.alimmdn.com/ldy/2017/8e4791ec-17b2-49e3-8a6f-8c7009aabe60.jpg\",\"content\":null,\"advertisementType\":\"2\",\"linkId\":\"1489325\",\"itemType\":\"1\",\"isCollect\":\"0\",\"price\":\"289.00\",\"memberPrice\":\"268.00\",\"svipLabel\":null,\"isPreSale\":\"0\",\"advertisementTitle\":null,\"discountType\":\"0\",\"isOpenItemProperty\":\"1\",\"height\":267,\"width\":375,\"advertisementWidth\":\"0\",\"linkValue\":null}]},{\"modularId\":136396,\"modularType\":\"0\",\"modularStyle\":\"2\",\"modularHeight\":\"387\",\"modularWidth\":\"0\",\"modularScale\":null,\"modularTitle\":\"\",\"modularSubTitle\":\"\",\"isShowSpace\":\"0\",\"modularDataList\":[{\"advertisementId\":2550982,\"title\":null,\"memo\":null,\"bannerUrl\":\"http://yycmedia.image.alimmdn.com/ldy/2017/6b7727d0-232c-4110-b025-8b74c9528e37.jpg\",\"content\":null,\"advertisementType\":\"2\",\"linkId\":\"1489327\",\"itemType\":\"1\",\"isCollect\":\"0\",\"price\":\"609.00\",\"memberPrice\":\"588.00\",\"svipLabel\":null,\"isPreSale\":\"0\",\"advertisementTitle\":null,\"discountType\":\"0\",\"isOpenItemProperty\":\"1\",\"height\":387,\"width\":375,\"advertisementWidth\":\"0\",\"linkValue\":null},{\"advertisementId\":2550983,\"title\":null,\"memo\":null,\"bannerUrl\":\"http://yycmedia.image.alimmdn.com/ldy/2017/bb4d5e70-9705-4a5e-bc58-a2a1f09106cb.jpg\",\"content\":null,\"advertisementType\":\"2\",\"linkId\":\"1489340\",\"itemType\":\"1\",\"isCollect\":\"0\",\"price\":\"179.00\",\"memberPrice\":\"159.00\",\"svipLabel\":null,\"isPreSale\":\"0\",\"advertisementTitle\":null,\"discountType\":\"0\",\"isOpenItemProperty\":\"1\",\"height\":387,\"width\":375,\"advertisementWidth\":\"0\",\"linkValue\":null}]}],\"isShowShoppingCart\":0,\"shareTitle\":null,\"deliveryTypeId\":1}"
}