{
  "Code": "000",
  "Message": "操作成功！",
  "Result": "{\"tmallShopName\":\"树懒熊\",\"total\":27,\"shareSubTitle\":null,\"title\":\"开门红\",\"distance\":\"575620.6860324187\",\"tmallShopLogo\":\"http://yycmedia.image.alimmdn.com/ldy/2017/01faea9d-43e3-4450-b5f3-995c8b040102.jpg\",\"shareIconUrl\":null,\"homeDataList\":[{\"modularId\":99736,\"modularType\":\"0\",\"modularStyle\":\"1\",\"modularHeight\":\"1077\",\"modularWidth\":\"0\",\"modularScale\":null,\"modularTitle\":\"\",\"modularSubTitle\":\"\",\"isShowSpace\":\"0\",\"modularDataList\":[{\"advertisementId\":2550935,\"title\":null,\"memo\":null,\"bannerUrl\":\"http://yycmedia.image.alimmdn.com/ldy/2017/349fab88-7f90-4b66-9cc2-e843e0ee2876.jpg\",\"content\":null,\"advertisementType\":\"0\",\"linkId\":\"0\",\"itemType\":null,\"isCollect\":\"0\",\"price\":null,\"memberPrice\":null,\"svipLabel\":null,\"isPreSale\":null,\"advertisementTitle\":null,\"discountType\":null,\"isOpenItemProperty\":null,\"height\":1077,\"width\":750,\"advertisementWidth\":\"0\",\"linkValue\":null}]},{\"modularId\":99739,\"modularType\":\"0\",\"modularStyle\":\"2\",\"modularHeight\":\"197\",\"modularWidth\":\"0\",\"modularScale\":null,\"modularTitle\":\"\",\"modularSubTitle\":\"\",\"isShowSpace\":\"0\",\"modularDataList\":[{\"advertisementId\":2550936,\"title\":null,\"memo\":null,\"bannerUrl\":\"http://yycmedia.image.alimmdn.com/ldy/2017/58f3a471-748f-4c21-9d2d-fcd1ee50838f.jpg\",\"content\":null,\"advertisementType\":\"19\",\"linkId\":\"39476\",\"itemType\":null,\"isCollect\":\"0\",\"price\":null,\"memberPrice\":null,\"svipLabel\":null,\"isPreSale\":null,\"advertisementTitle\":null,\"discountType\":null,\"isOpenItemProperty\":null,\"height\":197,\"width\":375,\"advertisementWidth\":\"0\",\"linkValue\":null},{\"advertisementId\":2550937,\"title\":null,\"memo\":null,\"bannerUrl\":\"http://yycmedia.image.alimmdn.com/ldy/2017/01afb5ef-aea2-49cb-b6ce-423b03abe776.jpg\",\"content\":null,\"advertisementType\":\"19\",\"linkId\":\"39477\",\"itemType\":null,\"isCollect\":\"0\",\"price\":null,\"memberPrice\":null,\"svipLabel\":null,\"isPreSale\":null,\"advertisementTitle\":null,\"discountType\":null,\"isOpenItemProperty\":null,\"height\":197,\"width\":375,\"advertisementWidth\":\"0\",\"linkValue\":null}]},{\"modularId\":115263,\"modularType\":\"0\",\"modularStyle\":\"0\",\"modularHeight\":\"90\",\"modularWidth\":\"0\",\"modularScale\":null,\"modularTitle\":\"\",\"modularSubTitle\":\"\",\"isShowSpace\":\"0\",\"modularDataList\":[{\"advertisementId\":2550938,\"title\":null,\"memo\":null,\"bannerUrl\":\"http://yycmedia.image.alimmdn.com/ldy/2017/aad6222e-9c37-4505-953d-aee6ee3b4789.jpg\",\"content\":null,\"advertisementType\":\"0\",\"linkId\":\"0\",\"itemType\":null,\"isCollect\":\"0\",\"price\":null,\"memberPrice\":null,\"svipLabel\":null,\"isPreSale\":null,\"advertisementTitle\":null,\"discountType\":null,\"isOpenItemProperty\":null,\"height\":90,\"width\":750,\"advertisementWidth\":\"0\",\"linkValue\":null}]},{\"modularId\":99741,\"modularType\":\"0\",\"modularStyle\":\"2\",\"modularHeight\":\"380\",\"modularWidth\":\"0\",\"modularScale\":null,\"modularTitle\":\"\",\"modularSubTitle\":\"\",\"isShowSpace\":\"0\",\"modularDataList\":[{\"advertisementId\":2550939,\"title\":null,\"memo\":null,\"bannerUrl\":\"http://yycmedia.image.alimmdn.com/ldy/2017/9f734f1a-63c4-49b0-96ab-e301e59e3ce0.jpg\",\"content\":null,\"advertisementType\":\"2\",\"linkId\":\"457176\",\"itemType\":\"1\",\"isCollect\":\"0\",\"price\":\"179.00\",\"memberPrice\":\"179.00\",\"svipLabel\":null,\"isPreSale\":\"0\",\"advertisementTitle\":null,\"discountType\":\"0\",\"isOpenItemProperty\":\"0\",\"height\":380,\"width\":375,\"advertisementWidth\":\"0\",\"linkValue\":null},{\"advertisementId\":2550940,\"title\":null,\"memo\":null,\"bannerUrl\":\"http://yycmedia.image.alimmdn.com/ldy/2017/09f45805-eb30-49e6-a993-4c2046e5ef27.jpg\",\"content\":null,\"advertisementType\":\"2\",\"linkId\":\"457175\",\"itemType\":\"1\",\"isCollect\":\"0\",\"price\":\"189.00\",\"memberPrice\":\"179.00\",\"svipLabel\":null,\"isPreSale\":\"0\",\"advertisementTitle\":null,\"discountType\":\"0\",\"isOpenItemProperty\":\"0\",\"height\":380,\"width\":375,\"advertisementWidth\":\"0\",\"linkValue\":null}]},{\"modularId\":99742,\"modularType\":\"0\",\"modularStyle\":\"2\",\"modularHeight\":\"276\",\"modularWidth\":\"0\",\"modularScale\":null,\"modularTitle\":\"\",\"modularSubTitle\":\"\",\"isShowSpace\":\"0\",\"modularDataList\":[{\"advertisementId\":2550941,\"title\":null,\"memo\":null,\"bannerUrl\":\"http://yycmedia.image.alimmdn.com/ldy/2017/8510b60f-2d64-4ee4-94b5-0058e8026d66.jpg\",\"content\":null,\"advertisementType\":\"2\",\"linkId\":\"464687\",\"itemType\":\"1\",\"isCollect\":\"0\",\"price\":\"129.00\",\"memberPrice\":\"129.00\",\"svipLabel\":null,\"isPreSale\":\"0\",\"advertisementTitle\":null,\"discountType\":\"0\",\"isOpenItemProperty\":\"0\",\"height\":276,\"width\":375,\"advertisementWidth\":\"0\",\"linkValue\":null},{\"advertisementId\":2550942,\"title\":null,\"memo\":null,\"bannerUrl\":\"http://yycmedia.image.alimmdn.com/ldy/2017/40c6fd8f-4347-406c-bd61-bd9ef9f78c2a.jpg\",\"content\":null,\"advertisementType\":\"2\",\"linkId\":\"463220\",\"itemType\":\"1\",\"isCollect\":\"0\",\"price\":\"223.00\",\"memberPrice\":\"223.00\",\"svipLabel\":null,\"isPreSale\":\"0\",\"advertisementTitle\":null,\"discountType\":\"0\",\"isOpenItemProperty\":\"0\",\"height\":276,\"width\":375,\"advertisementWidth\":\"0\",\"linkValue\":null}]},{\"modularId\":99743,\"modularType\":\"0\",\"modularStyle\":\"2\",\"modularHeight\":\"279\",\"modularWidth\":\"0\",\"modularScale\":null,\"modularTitle\":\"\",\"modularSubTitle\":\"\",\"isShowSpace\":\"0\",\"modularDataList\":[{\"advertisementId\":2550943,\"title\":null,\"memo\":null,\"bannerUrl\":\"http://yycmedia.image.alimmdn.com/ldy/2017/6f517be5-ed24-412b-a007-edb4ccab9626.jpg\",\"content\":null,\"advertisementType\":\"2\",\"linkId\":\"457171\",\"itemType\":\"1\",\"isCollect\":\"0\",\"price\":\"713.00\",\"memberPrice\":\"699.00\",\"svipLabel\":null,\"isPreSale\":\"0\",\"advertisementTitle\":null,\"discountType\":\"2\",\"isOpenItemProperty\":\"1\",\"height\":279,\"width\":375,\"advertisementWidth\":\"0\",\"linkValue\":null},{\"advertisementId\":2550944,\"title\":null,\"memo\":null,\"bannerUrl\":\"http://yycmedia.image.alimmdn.com/ldy/2017/cbeef2be-7889-4861-8ae1-8e56dd7bcda0.jpg\",\"content\":null,\"advertisementType\":\"2\",\"linkId\":\"457181\",\"itemType\":\"1\",\"isCollect\":\"0\",\"price\":\"249.00\",\"memberPrice\":\"239.00\",\"svipLabel\":null,\"isPreSale\":\"0\",\"advertisementTitle\":null,\"discountType\":\"0\",\"isOpenItemProperty\":\"0\",\"height\":279,\"width\":375,\"advertisementWidth\":\"0\",\"linkValue\":null}]},{\"modularId\":99745,\"modularType\":\"0\",\"modularStyle\":\"2\",\"modularHeight\":\"282\",\"modularWidth\":\"0\",\"modularScale\":null,\"modularTitle\":\"\",\"modularSubTitle\":\"\",\"isShowSpace\":\"0\",\"modularDataList\":[{\"advertisementId\":2550945,\"title\":null,\"memo\":null,\"bannerUrl\":\"http://yycmedia.image.alimmdn.com/ldy/2017/469d324d-acff-4b7f-958a-2d422811bad8.jpg\",\"content\":null,\"advertisementType\":\"2\",\"linkId\":\"457345\",\"itemType\":\"1\",\"isCollect\":\"0\",\"price\":\"115.00\",\"memberPrice\":\"109.00\",\"svipLabel\":null,\"isPreSale\":\"0\",\"advertisementTitle\":null,\"discountType\":\"0\",\"isOpenItemProperty\":\"1\",\"height\":282,\"width\":375,\"advertisementWidth\":\"0\",\"linkValue\":null},{\"advertisementId\":2550946,\"title\":null,\"memo\":null,\"bannerUrl\":\"http://yycmedia.image.alimmdn.com/ldy/2017/5c61e9d7-28c9-41c8-b944-ae6a1e47b310.jpg\",\"content\":null,\"advertisementType\":\"2\",\"linkId\":\"457346\",\"itemType\":\"1\",\"isCollect\":\"0\",\"price\":\"129.00\",\"memberPrice\":\"119.00\",\"svipLabel\":null,\"isPreSale\":\"0\",\"advertisementTitle\":null,\"discountType\":\"0\",\"isOpenItemProperty\":\"0\",\"height\":282,\"width\":375,\"advertisementWidth\":\"0\",\"linkValue\":null}]},{\"modularId\":99746,\"modularType\":\"0\",\"modularStyle\":\"2\",\"modularHeight\":\"276\",\"modularWidth\":\"0\",\"modularScale\":null,\"modularTitle\":\"\",\"modularSubTitle\":\"\",\"isShowSpace\":\"0\",\"modularDataList\":[{\"advertisementId\":2550947,\"title\":null,\"memo\":null,\"bannerUrl\":\"http://yycmedia.image.alimmdn.com/ldy/2017/f2e376ef-9524-4664-a569-0d2d84e56673.jpg\",\"content\":null,\"advertisementType\":\"2\",\"linkId\":\"457182\",\"itemType\":\"1\",\"isCollect\":\"0\",\"price\":\"219.00\",\"memberPrice\":\"209.00\",\"svipLabel\":null,\"isPreSale\":\"0\",\"advertisementTitle\":null,\"discountType\":\"0\",\"isOpenItemProperty\":\"0\",\"height\":276,\"width\":375,\"advertisementWidth\":\"0\",\"linkValue\":null},{\"advertisementId\":2550948,\"title\":null,\"memo\":null,\"bannerUrl\":\"http://yycmedia.image.alimmdn.com/ldy/2017/ee4d5165-cb7a-4d9c-a436-7045fc9d593e.jpg\",\"content\":null,\"advertisementType\":\"2\",\"linkId\":\"458856\",\"itemType\":\"1\",\"isCollect\":\"0\",\"price\":\"139.00\",\"memberPrice\":\"129.00\",\"svipLabel\":null,\"isPreSale\":\"0\",\"advertisementTitle\":null,\"discountType\":\"0\",\"isOpenItemProperty\":\"0\",\"height\":276,\"width\":375,\"advertisementWidth\":\"0\",\"linkValue\":null}]},{\"modularId\":99747,\"modularType\":\"0\",\"modularStyle\":\"2\",\"modularHeight\":\"280\",\"modularWidth\":\"0\",\"modularScale\":null,\"modularTitle\":\"\",\"modularSubTitle\":\"\",\"isShowSpace\":\"0\",\"modularDataList\":[{\"advertisementId\":2550949,\"title\":null,\"memo\":null,\"bannerUrl\":\"http://yycmedia.image.alimmdn.com/ldy/2017/b58f17f0-2e4a-4da2-9a7a-097116d6f1a6.jpg\",\"content\":null,\"advertisementType\":\"2\",\"linkId\":\"457177\",\"itemType\":\"1\",\"isCollect\":\"0\",\"price\":\"209.00\",\"memberPrice\":\"209.00\",\"svipLabel\":null,\"isPreSale\":\"0\",\"advertisementTitle\":null,\"discountType\":\"0\",\"isOpenItemProperty\":\"0\",\"height\":280,\"width\":375,\"advertisementWidth\":\"0\",\"linkValue\":null},{\"advertisementId\":2550950,\"title\":null,\"memo\":null,\"bannerUrl\":\"http://yycmedia.image.alimmdn.com/ldy/2017/8b44d022-413c-44b1-bc12-a947af05ad2c.jpg\",\"content\":null,\"advertisementType\":\"2\",\"linkId\":\"490129\",\"itemType\":\"1\",\"isCollect\":\"0\",\"price\":\"275.00\",\"memberPrice\":\"264.50\",\"svipLabel\":null,\"isPreSale\":\"0\",\"advertisementTitle\":null,\"discountType\":\"2\",\"isOpenItemProperty\":\"0\",\"height\":280,\"width\":375,\"advertisementWidth\":\"0\",\"linkValue\":null}]},{\"modularId\":99749,\"modularType\":\"0\",\"modularStyle\":\"2\",\"modularHeight\":\"281\",\"modularWidth\":\"0\",\"modularScale\":null,\"modularTitle\":\"\",\"modularSubTitle\":\"\",\"isShowSpace\":\"0\",\"modularDataList\":[{\"advertisementId\":2550951,\"title\":null,\"memo\":null,\"bannerUrl\":\"http://yycmedia.image.alimmdn.com/ldy/2017/516620ba-b84b-423b-aa17-ddd079c61cec.jpg\",\"content\":null,\"advertisementType\":\"2\",\"linkId\":\"474844\",\"itemType\":\"1\",\"isCollect\":\"0\",\"price\":\"616.00\",\"memberPrice\":\"609.00\",\"svipLabel\":null,\"isPreSale\":\"0\",\"advertisementTitle\":null,\"discountType\":\"0\",\"isOpenItemProperty\":\"1\",\"height\":281,\"width\":375,\"advertisementWidth\":\"0\",\"linkValue\":null},{\"advertisementId\":2550952,\"title\":null,\"memo\":null,\"bannerUrl\":\"http://yycmedia.image.alimmdn.com/ldy/2017/9e69180f-d9fd-4f41-b616-f79c3a72e32d.jpg\",\"content\":null,\"advertisementType\":\"2\",\"linkId\":\"457315\",\"itemType\":\"1\",\"isCollect\":\"0\",\"price\":\"139.00\",\"memberPrice\":\"129.00\",\"svipLabel\":null,\"isPreSale\":\"0\",\"advertisementTitle\":null,\"discountType\":\"0\",\"isOpenItemProperty\":\"0\",\"height\":281,\"width\":375,\"advertisementWidth\":\"0\",\"linkValue\":null}]}],\"isShowShoppingCart\":0,\"shareTitle\":null,\"deliveryTypeId\":1}"
}